{
  "rank 0, name": "",
  "rank 0, total level": 0,
  "rank 0, xp": 0,
  "rank 0, highestSkill": "",
  "rank 0, gameMode": "",
  "rank 1, name": "",
  "rank 1, total level": 0,
  "rank 1, xp": 0,
  "rank 1, highestSkill": "",
  "rank 1, gameMode": "",
  "rank 2, name": "",
  "rank 2, total level": 0,
  "rank 2, xp": 0,
  "rank 2, highestSkill": "",
  "rank 2, gameMode": "",
  "rank 3, name": "",
  "rank 3, total level": 0,
  "rank 3, xp": 0,
  "rank 3, highestSkill": "",
  "rank 3, gameMode": "",
  "rank 4, name": "",
  "rank 4, total level": 0,
  "rank 4, xp": 0,
  "rank 4, highestSkill": "",
  "rank 4, gameMode": "",
  "rank 5, name": "",
  "rank 5, total level": 0,
  "rank 5, xp": 0,
  "rank 5, highestSkill": "",
  "rank 5, gameMode": "",
  "rank 6, name": "",
  "rank 6, total level": 0,
  "rank 6, xp": 0,
  "rank 6, highestSkill": "",
  "rank 6, gameMode": "",
  "rank 7, name": "",
  "rank 7, total level": 0,
  "rank 7, xp": 0,
  "rank 7, highestSkill": "",
  "rank 7, gameMode": "",
  "rank 8, name": "",
  "rank 8, total level": 0,
  "rank 8, xp": 0,
  "rank 8, highestSkill": "",
  "rank 8, gameMode": "",
  "rank 9, name": "",
  "rank 9, total level": 0,
  "rank 9, xp": 0,
  "rank 9, highestSkill": "",
  "rank 9, gameMode": "",
  "rank 10, name": "",
  "rank 10, total level": 0,
  "rank 10, xp": 0,
  "rank 10, highestSkill": "",
  "rank 10, gameMode": "",
  "rank 11, name": "",
  "rank 11, total level": 0,
  "rank 11, xp": 0,
  "rank 11, highestSkill": "",
  "rank 11, gameMode": "",
  "rank 12, name": "",
  "rank 12, total level": 0,
  "rank 12, xp": 0,
  "rank 12, highestSkill": "",
  "rank 12, gameMode": "",
  "rank 13, name": "",
  "rank 13, total level": 0,
  "rank 13, xp": 0,
  "rank 13, highestSkill": "",
  "rank 13, gameMode": "",
  "rank 14, name": "",
  "rank 14, total level": 0,
  "rank 14, xp": 0,
  "rank 14, highestSkill": "",
  "rank 14, gameMode": "",
  "rank 15, name": "",
  "rank 15, total level": 0,
  "rank 15, xp": 0,
  "rank 15, highestSkill": "",
  "rank 15, gameMode": "",
  "rank 16, name": "",
  "rank 16, total level": 0,
  "rank 16, xp": 0,
  "rank 16, highestSkill": "",
  "rank 16, gameMode": "",
  "rank 17, name": "",
  "rank 17, total level": 0,
  "rank 17, xp": 0,
  "rank 17, highestSkill": "",
  "rank 17, gameMode": "",
  "rank 18, name": "",
  "rank 18, total level": 0,
  "rank 18, xp": 0,
  "rank 18, highestSkill": "",
  "rank 18, gameMode": "",
  "rank 19, name": "Zxc",
  "rank 19, total level": 708,
  "rank 19, xp": 91,
  "rank 19, highestSkill": "Attack 13m",
  "rank 19, gameMode": "NONE",
  "rank 20, name": "Qwe",
  "rank 20, total level": 708,
  "rank 20, xp": 91,
  "rank 20, highestSkill": "Attack 13m",
  "rank 20, gameMode": "NONE",
  "rank 21, name": "Sd",
  "rank 21, total level": 708,
  "rank 21, xp": 91,
  "rank 21, highestSkill": "Attack 13m",
  "rank 21, gameMode": "NONE",
  "rank 22, name": "Asd",
  "rank 22, total level": 708,
  "rank 22, xp": 91,
  "rank 22, highestSkill": "Attack 13m",
  "rank 22, gameMode": "NONE",
  "rank 23, name": "C",
  "rank 23, total level": 708,
  "rank 23, xp": 91,
  "rank 23, highestSkill": "Strength 13m",
  "rank 23, gameMode": "NONE",
  "rank 24, name": "Turtle",
  "rank 24, total level": 708,
  "rank 24, xp": 91,
  "rank 24, highestSkill": "Attack 13m",
  "rank 24, gameMode": "NONE",
  "rank 25, name": "Owain",
  "rank 25, total level": 708,
  "rank 25, xp": 91,
  "rank 25, highestSkill": "Attack 13m",
  "rank 25, gameMode": "NONE",
  "rank 26, name": "Big Turtle",
  "rank 26, total level": 708,
  "rank 26, xp": 91,
  "rank 26, highestSkill": "Attack 13m",
  "rank 26, gameMode": "NONE",
  "rank 27, name": "Mgt Madness",
  "rank 27, total level": 1894,
  "rank 27, xp": 388,
  "rank 27, highestSkill": "Ranged 69m",
  "rank 27, gameMode": "NORMAL",
  "rank 28, name": "M2",
  "rank 28, total level": 2080,
  "rank 28, xp": 297,
  "rank 28, highestSkill": "Ranged 17m",
  "rank 28, gameMode": "NONE",
  "rank 29, name": "B",
  "rank 29, total level": 2080,
  "rank 29, xp": 337,
  "rank 29, highestSkill": "Thieving 48m",
  "rank 29, gameMode": "NONE"
}